pyscaffold/__init__.py
pyscaffold/actions.py
pyscaffold/api.py
pyscaffold/cli.py
pyscaffold/dependencies.py
pyscaffold/exceptions.py
pyscaffold/file_system.py
pyscaffold/identification.py
pyscaffold/info.py
pyscaffold/log.py
pyscaffold/operations.py
pyscaffold/repo.py
pyscaffold/shell.py
pyscaffold/structure.py
pyscaffold/termui.py
pyscaffold/toml.py
pyscaffold/update.py
pyscaffold/extensions/__init__.py
pyscaffold/extensions/cirrus.py
pyscaffold/extensions/config.py
pyscaffold/extensions/github_actions.py
pyscaffold/extensions/gitlab_ci.py
pyscaffold/extensions/interactive.py
pyscaffold/extensions/namespace.py
pyscaffold/extensions/no_pyproject.py
pyscaffold/extensions/no_skeleton.py
pyscaffold/extensions/no_tox.py
pyscaffold/extensions/pre_commit.py
pyscaffold/extensions/venv.py
pyscaffold/templates/__init__.py
pyscaffold/templates/__init__.template
pyscaffold/templates/authors.template
pyscaffold/templates/changelog.template
pyscaffold/templates/cirrus.template
pyscaffold/templates/conftest_py.template
pyscaffold/templates/contributing.template
pyscaffold/templates/coveragerc.template
pyscaffold/templates/github_ci_workflow.template
pyscaffold/templates/gitignore.template
pyscaffold/templates/gitignore_empty.template
pyscaffold/templates/gitlab_ci.template
pyscaffold/templates/header_interactive.template
pyscaffold/templates/isort_cfg.template
pyscaffold/templates/license_affero_3.0.template
pyscaffold/templates/license_apache.template
pyscaffold/templates/license_artistic_2.0.template
pyscaffold/templates/license_bsd0.template
pyscaffold/templates/license_cc0_1.0.template
pyscaffold/templates/license_eclipse_1.0.template
pyscaffold/templates/license_gpl_2.0.template
pyscaffold/templates/license_gpl_3.0.template
pyscaffold/templates/license_isc.template
pyscaffold/templates/license_lgpl_2.1.template
pyscaffold/templates/license_lgpl_3.0.template
pyscaffold/templates/license_mit.template
pyscaffold/templates/license_mozilla.template
PyScaffold-4.5.dist-info/AUTHORS.rst
PyScaffold-4.5.dist-info/LICENSE.txt
PyScaffold-4.5.dist-info/METADATA
PyScaffold-4.5.dist-info/WHEEL
PyScaffold-4.5.dist-info/entry_points.txt
PyScaffold-4.5.dist-info/top_level.txt
PyScaffold-4.5.dist-info/RECORD
