Metadata-Version: 2.1
Name: PyScaffold
Version: 4.5
Summary: Template tool for putting up the scaffold of a Python project
Home-page: https://github.com/pyscaffold/pyscaffold/
Author: Florian Wilhelm
Author-email: Florian.Wilhelm@gmail.com
License: MIT
Project-URL: Documentation, https://pyscaffold.org/
Project-URL: Source, https://github.com/pyscaffold/pyscaffold/
Project-URL: Tracker, https://github.com/pyscaffold/pyscaffold/issues
Project-URL: Changelog, https://pyscaffold.org/en/latest/changelog.html
Project-URL: Conda-Forge, https://anaconda.org/conda-forge/pyscaffold
Project-URL: Download, https://pypi.org/project/PyScaffold/#files
Project-URL: Twitter, https://twitter.com/PyScaffold
Platform: any
Classifier: Development Status :: 5 - Production/Stable
Classifier: Topic :: Utilities
Classifier: Programming Language :: Python
Classifier: Programming Language :: Python :: 3
Classifier: Programming Language :: Python :: 3 :: Only
Classifier: Environment :: Console
Classifier: Intended Audience :: Developers
Classifier: License :: OSI Approved :: MIT License
Classifier: Operating System :: POSIX :: Linux
Classifier: Operating System :: Unix
Classifier: Operating System :: MacOS
Classifier: Operating System :: Microsoft :: Windows
Requires-Python: >=3.6
License-File: LICENSE.txt
License-File: AUTHORS.rst
Requires-Dist: platformdirs (<4,>=2)
Requires-Dist: configupdater (<4,>=3.0)
Requires-Dist: setuptools (>=46.1.0)
Requires-Dist: setuptools-scm (>=5)
Requires-Dist: tomlkit (<2,>=0.7.0)
Requires-Dist: packaging (>=20.7)
Requires-Dist: importlib-metadata ; python_version < "3.8"
Requires-Dist: colorama (>=0.4.4) ; sys_platform == "win32"
Provides-Extra: all
Requires-Dist: pyscaffoldext-markdown (>=0.4) ; extra == 'all'
Requires-Dist: pyscaffoldext-custom-extension (>=0.6) ; extra == 'all'
Requires-Dist: pyscaffoldext-dsproject (>=0.5) ; extra == 'all'
Requires-Dist: pyscaffoldext-django (>=0.1.1) ; extra == 'all'
Requires-Dist: pyscaffoldext-cookiecutter (>=0.1) ; extra == 'all'
Requires-Dist: pyscaffoldext-travis (>=0.3) ; extra == 'all'
Requires-Dist: virtualenv ; extra == 'all'
Requires-Dist: pre-commit ; extra == 'all'
Provides-Extra: ds
Requires-Dist: pyscaffoldext-dsproject (>=0.5) ; extra == 'ds'
Provides-Extra: md
Requires-Dist: pyscaffoldext-markdown (>=0.4) ; extra == 'md'
Provides-Extra: testing
Requires-Dist: setuptools ; extra == 'testing'
Requires-Dist: setuptools-scm[toml] ; extra == 'testing'
Requires-Dist: wheel ; extra == 'testing'
Requires-Dist: build ; extra == 'testing'
Requires-Dist: tomlkit ; extra == 'testing'
Requires-Dist: certifi ; extra == 'testing'
Requires-Dist: tox ; extra == 'testing'
Requires-Dist: pre-commit ; extra == 'testing'
Requires-Dist: sphinx ; extra == 'testing'
Requires-Dist: flake8 ; extra == 'testing'
Requires-Dist: virtualenv ; extra == 'testing'
Requires-Dist: pytest ; extra == 'testing'
Requires-Dist: pytest-cov ; extra == 'testing'
Requires-Dist: pytest-xdist ; extra == 'testing'
Requires-Dist: pytest-randomly ; extra == 'testing'
